{
  "name": "lottery-wheel",
  "version": "0.0.1",
  "author": "Przemyslaw Pierzchalka",
  "description": "Lottery wheel",
  "main": "index.js",
  "scripts": {
    "test": "echo \"Error: no test specified\" && exit 1"
  },
  "repository": {
    "type": "git",
    "url": "git+https://github.com/ppierzchalka/lottery-wheel.git"
  },
  "author": "",
  "license": "MIT",
  "bugs": {
    "url": "https://github.com/ppierzchalka/lottery-wheel/issues"
  },
  "homepage": "https://github.com/ppierzchalka/lottery-wheel#readme"
}
